Workbook
Name Aporte: Planilha1!$D$19
Name Patrimonio: Planilha1!$D$22
Name Qtd_Anos: Planilha1!$D$20
Name rendimento_carteira: Planilha1!$D$15
Name Salario: Planilha1!$D$14
Name Sugestao_Investimento: Planilha1!$D$16
Name Taxa_Mensal: Planilha1!$D$21
Name Tipo_Perfil: Planilha1!$C$33
Name Valor_Perfil: Planilha1!$C$34

Sheet Planilha1
B13: CONFIGURAÇÕES
B14: Salário | D14: 6000
B15: Rendimento Carteira | D15: 0.0089
B16: Sugestão Ide Investimento (30%) | D16: =Salario*30% -> 1800
B18: INVESTIMENTO MENSAL
B19: Quanto investir por mês? | D19: 1000
B20: Por quantos anos? | D20: 10
B21: Taxa de rendimento mensal? | D21: 0.01079
B22: Patrimônio acumulado? | D22: =FV(Taxa_Mensal,Qtd_Anos*12,Aporte*-1) -> 243284.21
B23: Dividendos mensais? | D23: =Patrimonio*rendimento_carteira -> 2165.2295
B25: CENÁRIOS DE INVESTIMENTO
B26: TEMPO | C26: PATRIMÔNIO | D26: DIVIDENDO MENSAL
A27: 2 | B27: Quanto em 2 anos? | C27: =FV($D$21,$A27*12,$D$19*-1) -> 27227.627 | D27: =C27*rendimento_carteira -> 242.32588
A28: 5 | B28: Quanto em 5 anos? | C28: =FV($D$21,$A28*12,$D$19*-1) -> 83776.914 | D28: =C28*rendimento_carteira -> 745.61453
A29: 10 | B29: Quanto em 10 anos? | C29: =FV($D$21,$A29*12,$D$19*-1) -> 243284.21 | D29: =C29*rendimento_carteira -> 2165.2295
A30: 20 | B30: Quanto em 20 anos? | C30: =FV($D$21,$A30*12,$D$19*-1) -> 1125198.4 | D30: =C30*rendimento_carteira -> 10014.266
A31: 30 | B31: Quanto em 30 anos? | C31: =FV($D$21,$A31*12,$D$19*-1) -> 4322169.7 | D31: =C31*rendimento_carteira -> 38467.31
B33: PERFIL | C33: Conservador
B34: VALOR A SER INVESTIDO POR MÊS | C34: =Aporte -> 1000
B36: TIPO DE FII | C36: PERCENTUAL SUGERIDO | D36: VALORES
B37: PAPEL | C37: =VLOOKUP(Tipo_Perfil&"-"&B37,Planilha2!$B:$E,4,0) -> 0.3 | D37: =C37*Valor_Perfil -> 300
B38: TIJOLO | C38: =VLOOKUP(Tipo_Perfil&"-"&B38,Planilha2!$B:$E,4,0) -> 0.5 | D38: =C38*Valor_Perfil -> 500
B39: HÍBRIDOS | C39: =VLOOKUP(Tipo_Perfil&"-"&B39,Planilha2!$B:$E,4,0) -> 0.1 | D39: =C39*Valor_Perfil -> 100
B40: FOF's | C40: =VLOOKUP(Tipo_Perfil&"-"&B40,Planilha2!$B:$E,4,0) -> 0.1 | D40: =C40*Valor_Perfil -> 100
B41: DESENVOLVIMENTO | C41: =VLOOKUP(Tipo_Perfil&"-"&B41,Planilha2!$B:$E,4,0) -> 0 | D41: =C41*Valor_Perfil -> 0
B42: HOTELARIA | C42: =VLOOKUP(Tipo_Perfil&"-"&B42,Planilha2!$B:$E,4,0) -> 0 | D42: =C42*Valor_Perfil -> 0
D43: =SUM(D37:D42) -> 1000
C45: Informações sobre Investimentos em FIIs

Sheet Planilha2
J1: %
B2: CHAVE COMPOSTA | C2: PERFIL | D2: TIPO DE FII | E2: % | I2: Moderado-HÍBRIDOS | J2: =VLOOKUP(I2,$B:$E,4,FALSE) -> 0.08
B3: =C3&"-"&D3 -> Conservador-PAPEL | C3: Conservador | D3: PAPEL | E3: 0.3
B4: =C4&"-"&D4 -> Conservador-TIJOLO | C4: Conservador | D4: TIJOLO | E4: 0.5
B5: =C5&"-"&D5 -> Conservador-HÍBRIDOS | C5: Conservador | D5: HÍBRIDOS | E5: 0.1
B6: =C6&"-"&D6 -> Conservador-FOF's | C6: Conservador | D6: FOF's | E6: 0.1
B7: =C7&"-"&D7 -> Conservador-DESENVOLVIMENTO | C7: Conservador | D7: DESENVOLVIMENTO | E7: 0
B8: =C8&"-"&D8 -> Conservador-HOTELARIA | C8: Conservador | D8: HOTELARIA | E8: 0
B9: =C9&"-"&D9 -> Moderado-PAPEL | C9: Moderado | D9: PAPEL | E9: 0.32
B10: =C10&"-"&D10 -> Moderado-TIJOLO | C10: Moderado | D10: TIJOLO | E10: 0.35
B11: =C11&"-"&D11 -> Moderado-HÍBRIDOS | C11: Moderado | D11: HÍBRIDOS | E11: 0.08
B12: =C12&"-"&D12 -> Moderado-FOF's | C12: Moderado | D12: FOF's | E12: 0.05
B13: =C13&"-"&D13 -> Moderado-DESENVOLVIMENTO | C13: Moderado | D13: DESENVOLVIMENTO | E13: 0.1
B14: =C14&"-"&D14 -> Moderado-HOTELARIA | C14: Moderado | D14: HOTELARIA | E14: 0.1
... B20: =C20&"-"&D20 -> Agressivo-HOTELARIA | C20: Agressivo | D20: HOTELARIA | E20: 0.1
